security_scan_invoker/__init__.py
security_scan_invoker/arg_parser_wrapper.py
security_scan_invoker/build_details.py
security_scan_invoker/build_details_fetcher.py
security_scan_invoker/iface_arg_parser.py
security_scan_invoker/iface_build_details_fetcher.py
security_scan_invoker/iface_veracode_api.py
security_scan_invoker/logging.conf
security_scan_invoker/main.py
security_scan_invoker/parser.py
security_scan_invoker/scanner_args.py
security_scan_invoker/veracode_api_wrapper.py
security_scan_invoker/veracode_scanner_app.py
tests/__init__.py
tests/fake_arg_parser.py
tests/fake_build_details_fetcher.py
tests/fake_veracode_api.py
tests/fakes.py
tests/test_build_details.py
tests/test_build_details_fetcher.py
tests/test_parser.py
tests/test_scanner_args.py
tests/test_veracode_api.py
tests/test_veracode_scanner_app.py
security_scan_invoker-1.1.0.dist-info/LICENSE
security_scan_invoker-1.1.0.dist-info/METADATA
security_scan_invoker-1.1.0.dist-info/WHEEL
security_scan_invoker-1.1.0.dist-info/entry_points.txt
security_scan_invoker-1.1.0.dist-info/top_level.txt
security_scan_invoker-1.1.0.dist-info/RECORD
