Metadata-Version: 2.1
Name: security-scan-invoker
Version: 1.1.0
Summary: Submits a Veracode scan if able. Will perform pre-scan checks to determine the
Project-URL: Source Code, https://github.com/JohnDeere/security-scan-invoker
License-File: LICENSE
Requires-Dist: requests
Requires-Dist: veracode-api-signing
Requires-Dist: xmltodict
Requires-Dist: black
